polos/__init__.py
polos/bpe_simple_vocab_16e6.txt.gz
polos/cli.py
polos/clip.py
polos/corpora.py
polos/metrics/__init__.py
polos/metrics/ranking_metrics.py
polos/metrics/regression_metrics.py
polos/model.py
polos/models/__init__.py
polos/models/encoders/__init__.py
polos/models/encoders/bert.py
polos/models/encoders/encoder_base.py
polos/models/encoders/xlmr.py
polos/models/estimators/__init__.py
polos/models/estimators/estimator_base.py
polos/models/estimators/polos_estimator.py
polos/models/estimators/quality_estimator.py
polos/models/model_base.py
polos/models/ranking/__init__.py
polos/models/ranking/polos_ranker.py
polos/models/ranking/ranking_base.py
polos/models/utils.py
polos/modules/__init__.py
polos/modules/activations.py
polos/modules/feedforward.py
polos/modules/scalar_mix.py
polos/schedulers.py
polos/simple_tokenizer.py
polos/tokenizers_/__init__.py
polos/tokenizers_/hf_tokenizer.py
polos/tokenizers_/tokenizer_base.py
polos/tokenizers_/xlmr_tokenizer.py
polos/trainer.py
pyproject.toml
polos-0.1.3.dist-info/METADATA
polos-0.1.3.dist-info/WHEEL
polos-0.1.3.dist-info/entry_points.txt
polos-0.1.3.dist-info/RECORD
