Metadata-Version: 2.1
Name: polos
Version: 0.1.3
Summary: [CVPR24] Polos: Multimodal Metric Learning from Human Feedback for Image Captioning
License: BSD-3-Clause-Clear
Author: Yuiga Wada
Author-email: yuigawada@gmail.com
Requires-Python: >3.9,<=3.10.0
Classifier: Development Status :: 4 - Beta
Classifier: Environment :: Console
Classifier: Intended Audience :: Science/Research
Classifier: License :: Other/Proprietary License
Classifier: Programming Language :: Python :: 3
Classifier: Programming Language :: Python :: 3.10
Classifier: Topic :: Scientific/Engineering :: Artificial Intelligence
Requires-Dist: PyYAML (==5.3.*)
Requires-Dist: click (>=8.1.7,<9.0.0)
Requires-Dist: fairseq (>=0.12.2,<0.13.0)
Requires-Dist: fsspec (==0.8.7)
Requires-Dist: ftfy (>=6.1.1,<7.0.0)
Requires-Dist: matplotlib (>=3.8.1,<4.0.0)
Requires-Dist: pandas (>=1.0.0,<2.0.0)
Requires-Dist: protobuf (<3.20.0)
Requires-Dist: psycopg2-binary (>=2.9.6,<3.0.0)
Requires-Dist: pycocoevalcap (>=1.2,<2.0)
Requires-Dist: pycocotools (>=2.0.7,<3.0.0)
Requires-Dist: pytorch-lightning (<=1.3)
Requires-Dist: pytorch-nlp (==0.5.0)
Requires-Dist: regex (>=2023.10.3,<2024.0.0)
Requires-Dist: scikit-learn (>=1.3.2,<2.0.0)
Requires-Dist: termcolor (>=2.3.0,<3.0.0)
Requires-Dist: torch (>=2.1.0,<3.0.0)
Requires-Dist: torchvision (>=0.16.0,<0.17.0)
Requires-Dist: transformers (==4.*)
Requires-Dist: wandb (>=0.15.12,<0.16.0)
